cloudcruise/__init__.py
cloudcruise/_default.py
cloudcruise/cloudcruise.py
cloudcruise/py.typed
cloudcruise/events/__init__.py
cloudcruise/events/types.py
cloudcruise/runs/__init__.py
cloudcruise/runs/client.py
cloudcruise/runs/types.py
cloudcruise/utils/async_queue.py
cloudcruise/utils/connection_manager.py
cloudcruise/utils/env.py
cloudcruise/utils/events.py
cloudcruise/utils/sse.py
cloudcruise/vault/__init__.py
cloudcruise/vault/client.py
cloudcruise/vault/types.py
cloudcruise/vault/utils.py
cloudcruise/webhook/__init__.py
cloudcruise/webhook/client.py
cloudcruise/webhook/types.py
cloudcruise/webhook/utils.py
cloudcruise/workflows/__init__.py
cloudcruise/workflows/client.py
cloudcruise/workflows/types.py
cloudcruise-0.0.1.dist-info/licenses/LICENSE
cloudcruise-0.0.1.dist-info/METADATA
cloudcruise-0.0.1.dist-info/WHEEL
cloudcruise-0.0.1.dist-info/top_level.txt
cloudcruise-0.0.1.dist-info/RECORD
