Metadata-Version: 2.4
Name: cloudcruise
Version: 0.0.1
Summary: The official CloudCruise Python SDK
Author-email: CloudCruise <founders@cloudcruise.com>
License: MIT License
Project-URL: Homepage, https://cloudcruise.com
Project-URL: Documentation, https://docs.cloudcruise.com
Project-URL: Repository, https://github.com/CloudCruise/cloudcruise-python
Project-URL: Issues, https://github.com/CloudCruise/cloudcruise-python/issues
Project-URL: Discord, https://discord.com/invite/MHjbUqedZF
Keywords: cloudcruise,sdk,automation,workflows,sse,webhook
Classifier: Programming Language :: Python :: 3
Classifier: Programming Language :: Python :: 3 :: Only
Classifier: License :: OSI Approved :: MIT License
Classifier: Operating System :: OS Independent
Classifier: Typing :: Typed
Requires-Python: >=3.10
License-File: LICENSE
Requires-Dist: requests>=2.31.0
Requires-Dist: cryptography>=41.0.0
Provides-Extra: dev
Requires-Dist: ruff>=0.1.0; extra == "dev"
Requires-Dist: mypy>=1.0.0; extra == "dev"
Requires-Dist: python-dotenv>=1.0.0; extra == "dev"
Requires-Dist: build>=1.0.0; extra == "dev"
Requires-Dist: twine>=4.0.0; extra == "dev"
Dynamic: license-file
